ldapdb/__init__.py
ldapdb/router.py
ldapdb/tests.py
ldapdb/version.py
ldapdb/backends/__init__.py
ldapdb/backends/ldap/__init__.py
ldapdb/backends/ldap/base.py
ldapdb/backends/ldap/compiler.py
ldapdb/models/__init__.py
ldapdb/models/base.py
ldapdb/models/fields.py
mprov_django_ldapdb-1.5.4.dist-info/AUTHORS
mprov_django_ldapdb-1.5.4.dist-info/LICENSE
mprov_django_ldapdb-1.5.4.dist-info/METADATA
mprov_django_ldapdb-1.5.4.dist-info/WHEEL
mprov_django_ldapdb-1.5.4.dist-info/top_level.txt
mprov_django_ldapdb-1.5.4.dist-info/RECORD
